[
  {
    "timestamp": 1778926233242,
    "marketId": "1.258242066",
    "selectionId": "18848403",
    "selectionName": "Diletta Cherubini",
    "lastTradedPrice": 3.6,
    "bsp": null,
    "inPlay": true
  },
  {
    "timestamp": 1778926233242,
    "marketId": "1.258242066",
    "selectionId": "2250861",
    "selectionName": "Vera Zvonareva",
    "lastTradedPrice": 1.37,
    "bsp": null,
    "inPlay": true
  },
  {
    "timestamp": 1778926323224,
    "marketId": "1.258242066",
    "selectionId": "18848403",
    "selectionName": "Diletta Cherubini",
    "lastTradedPrice": 4.5,
    "bsp": null,
    "inPlay": true
  },
  {
    "timestamp": 1778926323224,
    "marketId": "1.258242066",
    "selectionId": "2250861",
    "selectionName": "Vera Zvonareva",
    "lastTradedPrice": 1.28,
    "bsp": null,
    "inPlay": true
  },
  {
    "timestamp": 1778926413269,
    "marketId": "1.258242066",
    "selectionId": "18848403",
    "selectionName": "Diletta Cherubini",
    "lastTradedPrice": 5,
    "bsp": null,
    "inPlay": true
  },
  {
    "timestamp": 1778926413269,
    "marketId": "1.258242066",
    "selectionId": "2250861",
    "selectionName": "Vera Zvonareva",
    "lastTradedPrice": 1.24,
    "bsp": null,
    "inPlay": true
  },
  {
    "timestamp": 1778926503327,
    "marketId": "1.258242066",
    "selectionId": "18848403",
    "selectionName": "Diletta Cherubini",
    "lastTradedPrice": 4.9,
    "bsp": null,
    "inPlay": true
  },
  {
    "timestamp": 1778926503327,
    "marketId": "1.258242066",
    "selectionId": "2250861",
    "selectionName": "Vera Zvonareva",
    "lastTradedPrice": 1.24,
    "bsp": null,
    "inPlay": true
  },
  {
    "timestamp": 1778926593372,
    "marketId": "1.258242066",
    "selectionId": "18848403",
    "selectionName": "Diletta Cherubini",
    "lastTradedPrice": 6.4,
    "bsp": null,
    "inPlay": true
  },
  {
    "timestamp": 1778926593372,
    "marketId": "1.258242066",
    "selectionId": "2250861",
    "selectionName": "Vera Zvonareva",
    "lastTradedPrice": 1.18,
    "bsp": null,
    "inPlay": true
  },
  {
    "timestamp": 1778926773379,
    "marketId": "1.258242066",
    "selectionId": "18848403",
    "selectionName": "Diletta Cherubini",
    "lastTradedPrice": 5.2,
    "bsp": null,
    "inPlay": true
  },
  {
    "timestamp": 1778926773379,
    "marketId": "1.258242066",
    "selectionId": "2250861",
    "selectionName": "Vera Zvonareva",
    "lastTradedPrice": 1.23,
    "bsp": null,
    "inPlay": true
  },
  {
    "timestamp": 1778926773480,
    "marketId": "1.258242066",
    "selectionId": "18848403",
    "selectionName": "Diletta Cherubini",
    "lastTradedPrice": 5.2,
    "bsp": null,
    "inPlay": true
  },
  {
    "timestamp": 1778926773480,
    "marketId": "1.258242066",
    "selectionId": "2250861",
    "selectionName": "Vera Zvonareva",
    "lastTradedPrice": 1.23,
    "bsp": null,
    "inPlay": true
  },
  {
    "timestamp": 1778926863538,
    "marketId": "1.258242066",
    "selectionId": "18848403",
    "selectionName": "Diletta Cherubini",
    "lastTradedPrice": 7,
    "bsp": null,
    "inPlay": true
  },
  {
    "timestamp": 1778926863538,
    "marketId": "1.258242066",
    "selectionId": "2250861",
    "selectionName": "Vera Zvonareva",
    "lastTradedPrice": 1.16,
    "bsp": null,
    "inPlay": true
  },
  {
    "timestamp": 1778926953597,
    "marketId": "1.258242066",
    "selectionId": "18848403",
    "selectionName": "Diletta Cherubini",
    "lastTradedPrice": 5.9,
    "bsp": null,
    "inPlay": true
  },
  {
    "timestamp": 1778926953597,
    "marketId": "1.258242066",
    "selectionId": "2250861",
    "selectionName": "Vera Zvonareva",
    "lastTradedPrice": 1.2,
    "bsp": null,
    "inPlay": true
  },
  {
    "timestamp": 1778927043645,
    "marketId": "1.258242066",
    "selectionId": "18848403",
    "selectionName": "Diletta Cherubini",
    "lastTradedPrice": 4.9,
    "bsp": null,
    "inPlay": true
  },
  {
    "timestamp": 1778927043645,
    "marketId": "1.258242066",
    "selectionId": "2250861",
    "selectionName": "Vera Zvonareva",
    "lastTradedPrice": 1.24,
    "bsp": null,
    "inPlay": true
  },
  {
    "timestamp": 1778927133673,
    "marketId": "1.258242066",
    "selectionId": "18848403",
    "selectionName": "Diletta Cherubini",
    "lastTradedPrice": 4.9,
    "bsp": null,
    "inPlay": true
  },
  {
    "timestamp": 1778927133673,
    "marketId": "1.258242066",
    "selectionId": "2250861",
    "selectionName": "Vera Zvonareva",
    "lastTradedPrice": 1.25,
    "bsp": null,
    "inPlay": true
  },
  {
    "timestamp": 1778927223721,
    "marketId": "1.258242066",
    "selectionId": "18848403",
    "selectionName": "Diletta Cherubini",
    "lastTradedPrice": 6,
    "bsp": null,
    "inPlay": true
  },
  {
    "timestamp": 1778927223721,
    "marketId": "1.258242066",
    "selectionId": "2250861",
    "selectionName": "Vera Zvonareva",
    "lastTradedPrice": 1.18,
    "bsp": null,
    "inPlay": true
  },
  {
    "timestamp": 1778927403728,
    "marketId": "1.258242066",
    "selectionId": "18848403",
    "selectionName": "Diletta Cherubini",
    "lastTradedPrice": 4.4,
    "bsp": null,
    "inPlay": true
  },
  {
    "timestamp": 1778927403728,
    "marketId": "1.258242066",
    "selectionId": "2250861",
    "selectionName": "Vera Zvonareva",
    "lastTradedPrice": 1.27,
    "bsp": null,
    "inPlay": true
  },
  {
    "timestamp": 1778927403831,
    "marketId": "1.258242066",
    "selectionId": "18848403",
    "selectionName": "Diletta Cherubini",
    "lastTradedPrice": 4.4,
    "bsp": null,
    "inPlay": true
  },
  {
    "timestamp": 1778927403831,
    "marketId": "1.258242066",
    "selectionId": "2250861",
    "selectionName": "Vera Zvonareva",
    "lastTradedPrice": 1.27,
    "bsp": null,
    "inPlay": true
  },
  {
    "timestamp": 1778927493890,
    "marketId": "1.258242066",
    "selectionId": "18848403",
    "selectionName": "Diletta Cherubini",
    "lastTradedPrice": 4,
    "bsp": null,
    "inPlay": true
  },
  {
    "timestamp": 1778927493890,
    "marketId": "1.258242066",
    "selectionId": "2250861",
    "selectionName": "Vera Zvonareva",
    "lastTradedPrice": 1.32,
    "bsp": null,
    "inPlay": true
  },
  {
    "timestamp": 1778927583934,
    "marketId": "1.258242066",
    "selectionId": "18848403",
    "selectionName": "Diletta Cherubini",
    "lastTradedPrice": 4.9,
    "bsp": null,
    "inPlay": true
  },
  {
    "timestamp": 1778927583934,
    "marketId": "1.258242066",
    "selectionId": "2250861",
    "selectionName": "Vera Zvonareva",
    "lastTradedPrice": 1.23,
    "bsp": null,
    "inPlay": true
  },
  {
    "timestamp": 1778927673980,
    "marketId": "1.258242066",
    "selectionId": "18848403",
    "selectionName": "Diletta Cherubini",
    "lastTradedPrice": 4.8,
    "bsp": null,
    "inPlay": true
  },
  {
    "timestamp": 1778927673980,
    "marketId": "1.258242066",
    "selectionId": "2250861",
    "selectionName": "Vera Zvonareva",
    "lastTradedPrice": 1.21,
    "bsp": null,
    "inPlay": true
  },
  {
    "timestamp": 1778927764040,
    "marketId": "1.258242066",
    "selectionId": "18848403",
    "selectionName": "Diletta Cherubini",
    "lastTradedPrice": 5.9,
    "bsp": null,
    "inPlay": true
  },
  {
    "timestamp": 1778927764040,
    "marketId": "1.258242066",
    "selectionId": "2250861",
    "selectionName": "Vera Zvonareva",
    "lastTradedPrice": 1.2,
    "bsp": null,
    "inPlay": true
  },
  {
    "timestamp": 1778927854068,
    "marketId": "1.258242066",
    "selectionId": "18848403",
    "selectionName": "Diletta Cherubini",
    "lastTradedPrice": 6.8,
    "bsp": null,
    "inPlay": true
  },
  {
    "timestamp": 1778927854068,
    "marketId": "1.258242066",
    "selectionId": "2250861",
    "selectionName": "Vera Zvonareva",
    "lastTradedPrice": 1.16,
    "bsp": null,
    "inPlay": true
  },
  {
    "timestamp": 1778927944129,
    "marketId": "1.258242066",
    "selectionId": "18848403",
    "selectionName": "Diletta Cherubini",
    "lastTradedPrice": 8,
    "bsp": null,
    "inPlay": true
  },
  {
    "timestamp": 1778927944129,
    "marketId": "1.258242066",
    "selectionId": "2250861",
    "selectionName": "Vera Zvonareva",
    "lastTradedPrice": 1.13,
    "bsp": null,
    "inPlay": true
  },
  {
    "timestamp": 1778928034171,
    "marketId": "1.258242066",
    "selectionId": "18848403",
    "selectionName": "Diletta Cherubini",
    "lastTradedPrice": 6.8,
    "bsp": null,
    "inPlay": true
  },
  {
    "timestamp": 1778928034171,
    "marketId": "1.258242066",
    "selectionId": "2250861",
    "selectionName": "Vera Zvonareva",
    "lastTradedPrice": 1.14,
    "bsp": null,
    "inPlay": true
  },
  {
    "timestamp": 1778928124213,
    "marketId": "1.258242066",
    "selectionId": "18848403",
    "selectionName": "Diletta Cherubini",
    "lastTradedPrice": 8.4,
    "bsp": null,
    "inPlay": true
  },
  {
    "timestamp": 1778928124213,
    "marketId": "1.258242066",
    "selectionId": "2250861",
    "selectionName": "Vera Zvonareva",
    "lastTradedPrice": 1.11,
    "bsp": null,
    "inPlay": true
  },
  {
    "timestamp": 1778928214264,
    "marketId": "1.258242066",
    "selectionId": "18848403",
    "selectionName": "Diletta Cherubini",
    "lastTradedPrice": 9,
    "bsp": null,
    "inPlay": true
  },
  {
    "timestamp": 1778928214264,
    "marketId": "1.258242066",
    "selectionId": "2250861",
    "selectionName": "Vera Zvonareva",
    "lastTradedPrice": 1.12,
    "bsp": null,
    "inPlay": true
  },
  {
    "timestamp": 1778928304320,
    "marketId": "1.258242066",
    "selectionId": "18848403",
    "selectionName": "Diletta Cherubini",
    "lastTradedPrice": 11,
    "bsp": null,
    "inPlay": true
  },
  {
    "timestamp": 1778928304320,
    "marketId": "1.258242066",
    "selectionId": "2250861",
    "selectionName": "Vera Zvonareva",
    "lastTradedPrice": 1.09,
    "bsp": null,
    "inPlay": true
  },
  {
    "timestamp": 1778928394380,
    "marketId": "1.258242066",
    "selectionId": "18848403",
    "selectionName": "Diletta Cherubini",
    "lastTradedPrice": 12,
    "bsp": null,
    "inPlay": true
  },
  {
    "timestamp": 1778928394380,
    "marketId": "1.258242066",
    "selectionId": "2250861",
    "selectionName": "Vera Zvonareva",
    "lastTradedPrice": 1.08,
    "bsp": null,
    "inPlay": true
  },
  {
    "timestamp": 1778928484419,
    "marketId": "1.258242066",
    "selectionId": "18848403",
    "selectionName": "Diletta Cherubini",
    "lastTradedPrice": 13,
    "bsp": null,
    "inPlay": true
  },
  {
    "timestamp": 1778928484419,
    "marketId": "1.258242066",
    "selectionId": "2250861",
    "selectionName": "Vera Zvonareva",
    "lastTradedPrice": 1.08,
    "bsp": null,
    "inPlay": true
  },
  {
    "timestamp": 1778928574489,
    "marketId": "1.258242066",
    "selectionId": "18848403",
    "selectionName": "Diletta Cherubini",
    "lastTradedPrice": 13,
    "bsp": null,
    "inPlay": true
  },
  {
    "timestamp": 1778928574489,
    "marketId": "1.258242066",
    "selectionId": "2250861",
    "selectionName": "Vera Zvonareva",
    "lastTradedPrice": 1.08,
    "bsp": null,
    "inPlay": true
  },
  {
    "timestamp": 1778928664534,
    "marketId": "1.258242066",
    "selectionId": "18848403",
    "selectionName": "Diletta Cherubini",
    "lastTradedPrice": 13,
    "bsp": null,
    "inPlay": true
  },
  {
    "timestamp": 1778928664534,
    "marketId": "1.258242066",
    "selectionId": "2250861",
    "selectionName": "Vera Zvonareva",
    "lastTradedPrice": 1.07,
    "bsp": null,
    "inPlay": true
  },
  {
    "timestamp": 1778928754580,
    "marketId": "1.258242066",
    "selectionId": "18848403",
    "selectionName": "Diletta Cherubini",
    "lastTradedPrice": 11,
    "bsp": null,
    "inPlay": true
  },
  {
    "timestamp": 1778928754580,
    "marketId": "1.258242066",
    "selectionId": "2250861",
    "selectionName": "Vera Zvonareva",
    "lastTradedPrice": 1.09,
    "bsp": null,
    "inPlay": true
  },
  {
    "timestamp": 1778928844636,
    "marketId": "1.258242066",
    "selectionId": "18848403",
    "selectionName": "Diletta Cherubini",
    "lastTradedPrice": 10,
    "bsp": null,
    "inPlay": true
  },
  {
    "timestamp": 1778928844636,
    "marketId": "1.258242066",
    "selectionId": "2250861",
    "selectionName": "Vera Zvonareva",
    "lastTradedPrice": 1.07,
    "bsp": null,
    "inPlay": true
  },
  {
    "timestamp": 1778928934677,
    "marketId": "1.258242066",
    "selectionId": "18848403",
    "selectionName": "Diletta Cherubini",
    "lastTradedPrice": 10.5,
    "bsp": null,
    "inPlay": true
  },
  {
    "timestamp": 1778928934677,
    "marketId": "1.258242066",
    "selectionId": "2250861",
    "selectionName": "Vera Zvonareva",
    "lastTradedPrice": 1.1,
    "bsp": null,
    "inPlay": true
  },
  {
    "timestamp": 1778929114682,
    "marketId": "1.258242066",
    "selectionId": "18848403",
    "selectionName": "Diletta Cherubini",
    "lastTradedPrice": 10,
    "bsp": null,
    "inPlay": true
  },
  {
    "timestamp": 1778929114682,
    "marketId": "1.258242066",
    "selectionId": "2250861",
    "selectionName": "Vera Zvonareva",
    "lastTradedPrice": 1.07,
    "bsp": null,
    "inPlay": true
  },
  {
    "timestamp": 1778929114774,
    "marketId": "1.258242066",
    "selectionId": "18848403",
    "selectionName": "Diletta Cherubini",
    "lastTradedPrice": 10,
    "bsp": null,
    "inPlay": true
  },
  {
    "timestamp": 1778929114774,
    "marketId": "1.258242066",
    "selectionId": "2250861",
    "selectionName": "Vera Zvonareva",
    "lastTradedPrice": 1.07,
    "bsp": null,
    "inPlay": true
  },
  {
    "timestamp": 1778929204831,
    "marketId": "1.258242066",
    "selectionId": "18848403",
    "selectionName": "Diletta Cherubini",
    "lastTradedPrice": 20,
    "bsp": null,
    "inPlay": true
  },
  {
    "timestamp": 1778929204831,
    "marketId": "1.258242066",
    "selectionId": "2250861",
    "selectionName": "Vera Zvonareva",
    "lastTradedPrice": 1.04,
    "bsp": null,
    "inPlay": true
  },
  {
    "timestamp": 1778929384839,
    "marketId": "1.258242066",
    "selectionId": "18848403",
    "selectionName": "Diletta Cherubini",
    "lastTradedPrice": 22,
    "bsp": null,
    "inPlay": true
  },
  {
    "timestamp": 1778929384839,
    "marketId": "1.258242066",
    "selectionId": "2250861",
    "selectionName": "Vera Zvonareva",
    "lastTradedPrice": 1.02,
    "bsp": null,
    "inPlay": true
  },
  {
    "timestamp": 1778929384938,
    "marketId": "1.258242066",
    "selectionId": "18848403",
    "selectionName": "Diletta Cherubini",
    "lastTradedPrice": 22,
    "bsp": null,
    "inPlay": true
  },
  {
    "timestamp": 1778929384938,
    "marketId": "1.258242066",
    "selectionId": "2250861",
    "selectionName": "Vera Zvonareva",
    "lastTradedPrice": 1.02,
    "bsp": null,
    "inPlay": true
  },
  {
    "timestamp": 1778929474978,
    "marketId": "1.258242066",
    "selectionId": "18848403",
    "selectionName": "Diletta Cherubini",
    "lastTradedPrice": 32,
    "bsp": null,
    "inPlay": true
  },
  {
    "timestamp": 1778929474978,
    "marketId": "1.258242066",
    "selectionId": "2250861",
    "selectionName": "Vera Zvonareva",
    "lastTradedPrice": 1.03,
    "bsp": null,
    "inPlay": true
  },
  {
    "timestamp": 1778929565038,
    "marketId": "1.258242066",
    "selectionId": "18848403",
    "selectionName": "Diletta Cherubini",
    "lastTradedPrice": 17,
    "bsp": null,
    "inPlay": true
  },
  {
    "timestamp": 1778929565038,
    "marketId": "1.258242066",
    "selectionId": "2250861",
    "selectionName": "Vera Zvonareva",
    "lastTradedPrice": 1.04,
    "bsp": null,
    "inPlay": true
  },
  {
    "timestamp": 1778929655071,
    "marketId": "1.258242066",
    "selectionId": "18848403",
    "selectionName": "Diletta Cherubini",
    "lastTradedPrice": 32,
    "bsp": null,
    "inPlay": true
  },
  {
    "timestamp": 1778929655071,
    "marketId": "1.258242066",
    "selectionId": "2250861",
    "selectionName": "Vera Zvonareva",
    "lastTradedPrice": 1.03,
    "bsp": null,
    "inPlay": true
  },
  {
    "timestamp": 1778929745115,
    "marketId": "1.258242066",
    "selectionId": "18848403",
    "selectionName": "Diletta Cherubini",
    "lastTradedPrice": 29,
    "bsp": null,
    "inPlay": true
  },
  {
    "timestamp": 1778929745115,
    "marketId": "1.258242066",
    "selectionId": "2250861",
    "selectionName": "Vera Zvonareva",
    "lastTradedPrice": 1.01,
    "bsp": null,
    "inPlay": true
  },
  {
    "timestamp": 1778929925122,
    "marketId": "1.258242066",
    "selectionId": "18848403",
    "selectionName": "Diletta Cherubini",
    "lastTradedPrice": 29,
    "bsp": null,
    "inPlay": true
  },
  {
    "timestamp": 1778929925122,
    "marketId": "1.258242066",
    "selectionId": "2250861",
    "selectionName": "Vera Zvonareva",
    "lastTradedPrice": 1.03,
    "bsp": null,
    "inPlay": true
  },
  {
    "timestamp": 1778929925220,
    "marketId": "1.258242066",
    "selectionId": "18848403",
    "selectionName": "Diletta Cherubini",
    "lastTradedPrice": 29,
    "bsp": null,
    "inPlay": true
  },
  {
    "timestamp": 1778929925220,
    "marketId": "1.258242066",
    "selectionId": "2250861",
    "selectionName": "Vera Zvonareva",
    "lastTradedPrice": 1.03,
    "bsp": null,
    "inPlay": true
  },
  {
    "timestamp": 1778930015246,
    "marketId": "1.258242066",
    "selectionId": "18848403",
    "selectionName": "Diletta Cherubini",
    "lastTradedPrice": 60,
    "bsp": null,
    "inPlay": true
  },
  {
    "timestamp": 1778930015246,
    "marketId": "1.258242066",
    "selectionId": "2250861",
    "selectionName": "Vera Zvonareva",
    "lastTradedPrice": 1.01,
    "bsp": null,
    "inPlay": true
  },
  {
    "timestamp": 1778930105295,
    "marketId": "1.258242066",
    "selectionId": "18848403",
    "selectionName": "Diletta Cherubini",
    "lastTradedPrice": 75,
    "bsp": null,
    "inPlay": true
  },
  {
    "timestamp": 1778930105295,
    "marketId": "1.258242066",
    "selectionId": "2250861",
    "selectionName": "Vera Zvonareva",
    "lastTradedPrice": 1.01,
    "bsp": null,
    "inPlay": true
  },
  {
    "timestamp": 1778930285302,
    "marketId": "1.258242066",
    "selectionId": "18848403",
    "selectionName": "Diletta Cherubini",
    "lastTradedPrice": 75,
    "bsp": null,
    "inPlay": true
  },
  {
    "timestamp": 1778930285302,
    "marketId": "1.258242066",
    "selectionId": "2250861",
    "selectionName": "Vera Zvonareva",
    "lastTradedPrice": 0,
    "bsp": null,
    "inPlay": true
  },
  {
    "timestamp": 1778930285440,
    "marketId": "1.258242066",
    "selectionId": "18848403",
    "selectionName": "Diletta Cherubini",
    "lastTradedPrice": 75,
    "bsp": null,
    "inPlay": true
  },
  {
    "timestamp": 1778930285440,
    "marketId": "1.258242066",
    "selectionId": "2250861",
    "selectionName": "Vera Zvonareva",
    "lastTradedPrice": 0,
    "bsp": null,
    "inPlay": true
  },
  {
    "timestamp": 1778930465446,
    "marketId": "1.258242066",
    "selectionId": "18848403",
    "selectionName": "Diletta Cherubini",
    "lastTradedPrice": 150,
    "bsp": null,
    "inPlay": true
  },
  {
    "timestamp": 1778930465446,
    "marketId": "1.258242066",
    "selectionId": "2250861",
    "selectionName": "Vera Zvonareva",
    "lastTradedPrice": 0,
    "bsp": null,
    "inPlay": true
  },
  {
    "timestamp": 1778930465498,
    "marketId": "1.258242066",
    "selectionId": "18848403",
    "selectionName": "Diletta Cherubini",
    "lastTradedPrice": 150,
    "bsp": null,
    "inPlay": true
  },
  {
    "timestamp": 1778930465498,
    "marketId": "1.258242066",
    "selectionId": "2250861",
    "selectionName": "Vera Zvonareva",
    "lastTradedPrice": 0,
    "bsp": null,
    "inPlay": true
  },
  {
    "timestamp": 1778930555562,
    "marketId": "1.258242066",
    "selectionId": "18848403",
    "selectionName": "Diletta Cherubini",
    "lastTradedPrice": 130,
    "bsp": null,
    "inPlay": true
  },
  {
    "timestamp": 1778930555562,
    "marketId": "1.258242066",
    "selectionId": "2250861",
    "selectionName": "Vera Zvonareva",
    "lastTradedPrice": 0,
    "bsp": null,
    "inPlay": true
  },
  {
    "timestamp": 1778930645628,
    "marketId": "1.258242066",
    "selectionId": "18848403",
    "selectionName": "Diletta Cherubini",
    "lastTradedPrice": 1.01,
    "bsp": null,
    "inPlay": true
  },
  {
    "timestamp": 1778930645628,
    "marketId": "1.258242066",
    "selectionId": "2250861",
    "selectionName": "Vera Zvonareva",
    "lastTradedPrice": 0,
    "bsp": null,
    "inPlay": true
  }
]