[
  {
    "timestamp": 1774499931540,
    "marketId": "1.255828444",
    "selectionId": "12337529",
    "selectionName": "Mananchaya Sawangkaew",
    "lastTradedPrice": 1.01,
    "bsp": null,
    "inPlay": true
  },
  {
    "timestamp": 1774500111482,
    "marketId": "1.255828444",
    "selectionId": "20240136",
    "selectionName": "Martyna Kubka",
    "lastTradedPrice": 1.87,
    "bsp": null,
    "inPlay": true
  },
  {
    "timestamp": 1774500111482,
    "marketId": "1.255828444",
    "selectionId": "12337529",
    "selectionName": "Mananchaya Sawangkaew",
    "lastTradedPrice": 1.1,
    "bsp": null,
    "inPlay": true
  },
  {
    "timestamp": 1774500232750,
    "marketId": "1.255828444",
    "selectionId": "20240136",
    "selectionName": "Martyna Kubka",
    "lastTradedPrice": 1.7,
    "bsp": null,
    "inPlay": true
  },
  {
    "timestamp": 1774500232750,
    "marketId": "1.255828444",
    "selectionId": "12337529",
    "selectionName": "Mananchaya Sawangkaew",
    "lastTradedPrice": 2.3,
    "bsp": null,
    "inPlay": true
  },
  {
    "timestamp": 1774500412752,
    "marketId": "1.255828444",
    "selectionId": "20240136",
    "selectionName": "Martyna Kubka",
    "lastTradedPrice": 1.61,
    "bsp": null,
    "inPlay": true
  },
  {
    "timestamp": 1774500412752,
    "marketId": "1.255828444",
    "selectionId": "12337529",
    "selectionName": "Mananchaya Sawangkaew",
    "lastTradedPrice": 1.1,
    "bsp": null,
    "inPlay": true
  },
  {
    "timestamp": 1774500534021,
    "marketId": "1.255828444",
    "selectionId": "20240136",
    "selectionName": "Martyna Kubka",
    "lastTradedPrice": 1.82,
    "bsp": null,
    "inPlay": true
  },
  {
    "timestamp": 1774500534021,
    "marketId": "1.255828444",
    "selectionId": "12337529",
    "selectionName": "Mananchaya Sawangkaew",
    "lastTradedPrice": 2.08,
    "bsp": null,
    "inPlay": true
  },
  {
    "timestamp": 1774500714022,
    "marketId": "1.255828444",
    "selectionId": "20240136",
    "selectionName": "Martyna Kubka",
    "lastTradedPrice": 1.64,
    "bsp": null,
    "inPlay": true
  },
  {
    "timestamp": 1774500714022,
    "marketId": "1.255828444",
    "selectionId": "12337529",
    "selectionName": "Mananchaya Sawangkaew",
    "lastTradedPrice": 2.52,
    "bsp": null,
    "inPlay": true
  },
  {
    "timestamp": 1774500835297,
    "marketId": "1.255828444",
    "selectionId": "20240136",
    "selectionName": "Martyna Kubka",
    "lastTradedPrice": 1.69,
    "bsp": null,
    "inPlay": true
  },
  {
    "timestamp": 1774500835297,
    "marketId": "1.255828444",
    "selectionId": "12337529",
    "selectionName": "Mananchaya Sawangkaew",
    "lastTradedPrice": 2.18,
    "bsp": null,
    "inPlay": true
  },
  {
    "timestamp": 1774501015298,
    "marketId": "1.255828444",
    "selectionId": "20240136",
    "selectionName": "Martyna Kubka",
    "lastTradedPrice": 1.51,
    "bsp": null,
    "inPlay": true
  },
  {
    "timestamp": 1774501015298,
    "marketId": "1.255828444",
    "selectionId": "12337529",
    "selectionName": "Mananchaya Sawangkaew",
    "lastTradedPrice": 2.48,
    "bsp": null,
    "inPlay": true
  },
  {
    "timestamp": 1774501136637,
    "marketId": "1.255828444",
    "selectionId": "20240136",
    "selectionName": "Martyna Kubka",
    "lastTradedPrice": 1.41,
    "bsp": null,
    "inPlay": true
  },
  {
    "timestamp": 1774501136637,
    "marketId": "1.255828444",
    "selectionId": "12337529",
    "selectionName": "Mananchaya Sawangkaew",
    "lastTradedPrice": 3.3,
    "bsp": null,
    "inPlay": true
  },
  {
    "timestamp": 1774501316638,
    "marketId": "1.255828444",
    "selectionId": "20240136",
    "selectionName": "Martyna Kubka",
    "lastTradedPrice": 1.39,
    "bsp": null,
    "inPlay": true
  },
  {
    "timestamp": 1774501316638,
    "marketId": "1.255828444",
    "selectionId": "12337529",
    "selectionName": "Mananchaya Sawangkaew",
    "lastTradedPrice": 2.98,
    "bsp": null,
    "inPlay": true
  },
  {
    "timestamp": 1774501437887,
    "marketId": "1.255828444",
    "selectionId": "20240136",
    "selectionName": "Martyna Kubka",
    "lastTradedPrice": 1.38,
    "bsp": null,
    "inPlay": true
  },
  {
    "timestamp": 1774501437887,
    "marketId": "1.255828444",
    "selectionId": "12337529",
    "selectionName": "Mananchaya Sawangkaew",
    "lastTradedPrice": 3.55,
    "bsp": null,
    "inPlay": true
  },
  {
    "timestamp": 1774501617888,
    "marketId": "1.255828444",
    "selectionId": "20240136",
    "selectionName": "Martyna Kubka",
    "lastTradedPrice": 1.43,
    "bsp": null,
    "inPlay": true
  },
  {
    "timestamp": 1774501617888,
    "marketId": "1.255828444",
    "selectionId": "12337529",
    "selectionName": "Mananchaya Sawangkaew",
    "lastTradedPrice": 2.6,
    "bsp": null,
    "inPlay": true
  },
  {
    "timestamp": 1774501739140,
    "marketId": "1.255828444",
    "selectionId": "20240136",
    "selectionName": "Martyna Kubka",
    "lastTradedPrice": 1.61,
    "bsp": null,
    "inPlay": true
  },
  {
    "timestamp": 1774501739140,
    "marketId": "1.255828444",
    "selectionId": "12337529",
    "selectionName": "Mananchaya Sawangkaew",
    "lastTradedPrice": 2.18,
    "bsp": null,
    "inPlay": true
  },
  {
    "timestamp": 1774501919142,
    "marketId": "1.255828444",
    "selectionId": "20240136",
    "selectionName": "Martyna Kubka",
    "lastTradedPrice": 1.49,
    "bsp": null,
    "inPlay": true
  },
  {
    "timestamp": 1774501919142,
    "marketId": "1.255828444",
    "selectionId": "12337529",
    "selectionName": "Mananchaya Sawangkaew",
    "lastTradedPrice": 2.98,
    "bsp": null,
    "inPlay": true
  },
  {
    "timestamp": 1774502040521,
    "marketId": "1.255828444",
    "selectionId": "20240136",
    "selectionName": "Martyna Kubka",
    "lastTradedPrice": 1.49,
    "bsp": null,
    "inPlay": true
  },
  {
    "timestamp": 1774502040521,
    "marketId": "1.255828444",
    "selectionId": "12337529",
    "selectionName": "Mananchaya Sawangkaew",
    "lastTradedPrice": 2.98,
    "bsp": null,
    "inPlay": true
  },
  {
    "timestamp": 1774502220522,
    "marketId": "1.255828444",
    "selectionId": "20240136",
    "selectionName": "Martyna Kubka",
    "lastTradedPrice": 1.17,
    "bsp": null,
    "inPlay": true
  },
  {
    "timestamp": 1774502220522,
    "marketId": "1.255828444",
    "selectionId": "12337529",
    "selectionName": "Mananchaya Sawangkaew",
    "lastTradedPrice": 5.5,
    "bsp": null,
    "inPlay": true
  },
  {
    "timestamp": 1774502341772,
    "marketId": "1.255828444",
    "selectionId": "20240136",
    "selectionName": "Martyna Kubka",
    "lastTradedPrice": 1.13,
    "bsp": null,
    "inPlay": true
  },
  {
    "timestamp": 1774502341772,
    "marketId": "1.255828444",
    "selectionId": "12337529",
    "selectionName": "Mananchaya Sawangkaew",
    "lastTradedPrice": 6.8,
    "bsp": null,
    "inPlay": true
  },
  {
    "timestamp": 1774502521773,
    "marketId": "1.255828444",
    "selectionId": "20240136",
    "selectionName": "Martyna Kubka",
    "lastTradedPrice": 1.06,
    "bsp": null,
    "inPlay": true
  },
  {
    "timestamp": 1774502521773,
    "marketId": "1.255828444",
    "selectionId": "12337529",
    "selectionName": "Mananchaya Sawangkaew",
    "lastTradedPrice": 8.4,
    "bsp": null,
    "inPlay": true
  },
  {
    "timestamp": 1774502643163,
    "marketId": "1.255828444",
    "selectionId": "20240136",
    "selectionName": "Martyna Kubka",
    "lastTradedPrice": 1.13,
    "bsp": null,
    "inPlay": true
  },
  {
    "timestamp": 1774502643163,
    "marketId": "1.255828444",
    "selectionId": "12337529",
    "selectionName": "Mananchaya Sawangkaew",
    "lastTradedPrice": 6.4,
    "bsp": null,
    "inPlay": true
  },
  {
    "timestamp": 1774502823164,
    "marketId": "1.255828444",
    "selectionId": "20240136",
    "selectionName": "Martyna Kubka",
    "lastTradedPrice": 1.01,
    "bsp": null,
    "inPlay": true
  },
  {
    "timestamp": 1774502823164,
    "marketId": "1.255828444",
    "selectionId": "12337529",
    "selectionName": "Mananchaya Sawangkaew",
    "lastTradedPrice": 16.5,
    "bsp": null,
    "inPlay": true
  },
  {
    "timestamp": 1774502944452,
    "marketId": "1.255828444",
    "selectionId": "20240136",
    "selectionName": "Martyna Kubka",
    "lastTradedPrice": 0,
    "bsp": null,
    "inPlay": true
  },
  {
    "timestamp": 1774502944452,
    "marketId": "1.255828444",
    "selectionId": "12337529",
    "selectionName": "Mananchaya Sawangkaew",
    "lastTradedPrice": 1.1,
    "bsp": null,
    "inPlay": true
  },
  {
    "timestamp": 1774503124453,
    "marketId": "1.255828444",
    "selectionId": "20240136",
    "selectionName": "Martyna Kubka",
    "lastTradedPrice": 0,
    "bsp": null,
    "inPlay": true
  },
  {
    "timestamp": 1774503124453,
    "marketId": "1.255828444",
    "selectionId": "12337529",
    "selectionName": "Mananchaya Sawangkaew",
    "lastTradedPrice": 1.1,
    "bsp": null,
    "inPlay": true
  },
  {
    "timestamp": 1774503245733,
    "marketId": "1.255828444",
    "selectionId": "20240136",
    "selectionName": "Martyna Kubka",
    "lastTradedPrice": 0,
    "bsp": null,
    "inPlay": true
  },
  {
    "timestamp": 1774503245733,
    "marketId": "1.255828444",
    "selectionId": "12337529",
    "selectionName": "Mananchaya Sawangkaew",
    "lastTradedPrice": 1.1,
    "bsp": null,
    "inPlay": true
  },
  {
    "timestamp": 1774503425734,
    "marketId": "1.255828444",
    "selectionId": "20240136",
    "selectionName": "Martyna Kubka",
    "lastTradedPrice": 0,
    "bsp": null,
    "inPlay": true
  },
  {
    "timestamp": 1774503425734,
    "marketId": "1.255828444",
    "selectionId": "12337529",
    "selectionName": "Mananchaya Sawangkaew",
    "lastTradedPrice": 0,
    "bsp": null,
    "inPlay": true
  }
]