[
  {
    "timestamp": 1779612163010,
    "marketId": "1.258542774",
    "selectionId": "38145316",
    "selectionName": "Giorgio Tabacco",
    "lastTradedPrice": 2.02,
    "bsp": null,
    "inPlay": true
  },
  {
    "timestamp": 1779612163010,
    "marketId": "1.258542774",
    "selectionId": "8713660",
    "selectionName": "Eero Vasa",
    "lastTradedPrice": 1.9,
    "bsp": null,
    "inPlay": true
  },
  {
    "timestamp": 1779612252994,
    "marketId": "1.258542774",
    "selectionId": "38145316",
    "selectionName": "Giorgio Tabacco",
    "lastTradedPrice": 2.34,
    "bsp": null,
    "inPlay": true
  },
  {
    "timestamp": 1779612252994,
    "marketId": "1.258542774",
    "selectionId": "8713660",
    "selectionName": "Eero Vasa",
    "lastTradedPrice": 1.7,
    "bsp": null,
    "inPlay": true
  },
  {
    "timestamp": 1779612432998,
    "marketId": "1.258542774",
    "selectionId": "38145316",
    "selectionName": "Giorgio Tabacco",
    "lastTradedPrice": 2.34,
    "bsp": null,
    "inPlay": true
  },
  {
    "timestamp": 1779612432998,
    "marketId": "1.258542774",
    "selectionId": "8713660",
    "selectionName": "Eero Vasa",
    "lastTradedPrice": 1.7,
    "bsp": null,
    "inPlay": true
  },
  {
    "timestamp": 1779612612999,
    "marketId": "1.258542774",
    "selectionId": "38145316",
    "selectionName": "Giorgio Tabacco",
    "lastTradedPrice": 2.18,
    "bsp": null,
    "inPlay": true
  },
  {
    "timestamp": 1779612612999,
    "marketId": "1.258542774",
    "selectionId": "8713660",
    "selectionName": "Eero Vasa",
    "lastTradedPrice": 1.79,
    "bsp": null,
    "inPlay": true
  },
  {
    "timestamp": 1779612793002,
    "marketId": "1.258542774",
    "selectionId": "38145316",
    "selectionName": "Giorgio Tabacco",
    "lastTradedPrice": 2.24,
    "bsp": null,
    "inPlay": true
  },
  {
    "timestamp": 1779612793002,
    "marketId": "1.258542774",
    "selectionId": "8713660",
    "selectionName": "Eero Vasa",
    "lastTradedPrice": 1.75,
    "bsp": null,
    "inPlay": true
  },
  {
    "timestamp": 1779612973004,
    "marketId": "1.258542774",
    "selectionId": "38145316",
    "selectionName": "Giorgio Tabacco",
    "lastTradedPrice": 2.4,
    "bsp": null,
    "inPlay": true
  },
  {
    "timestamp": 1779612973004,
    "marketId": "1.258542774",
    "selectionId": "8713660",
    "selectionName": "Eero Vasa",
    "lastTradedPrice": 1.67,
    "bsp": null,
    "inPlay": true
  },
  {
    "timestamp": 1779613153005,
    "marketId": "1.258542774",
    "selectionId": "38145316",
    "selectionName": "Giorgio Tabacco",
    "lastTradedPrice": 2.3,
    "bsp": null,
    "inPlay": true
  },
  {
    "timestamp": 1779613153005,
    "marketId": "1.258542774",
    "selectionId": "8713660",
    "selectionName": "Eero Vasa",
    "lastTradedPrice": 1.49,
    "bsp": null,
    "inPlay": true
  },
  {
    "timestamp": 1779613243406,
    "marketId": "1.258542774",
    "selectionId": "38145316",
    "selectionName": "Giorgio Tabacco",
    "lastTradedPrice": 2.18,
    "bsp": null,
    "inPlay": true
  },
  {
    "timestamp": 1779613243406,
    "marketId": "1.258542774",
    "selectionId": "8713660",
    "selectionName": "Eero Vasa",
    "lastTradedPrice": 1.81,
    "bsp": null,
    "inPlay": true
  },
  {
    "timestamp": 1779613423408,
    "marketId": "1.258542774",
    "selectionId": "38145316",
    "selectionName": "Giorgio Tabacco",
    "lastTradedPrice": 1.85,
    "bsp": null,
    "inPlay": true
  },
  {
    "timestamp": 1779613423408,
    "marketId": "1.258542774",
    "selectionId": "8713660",
    "selectionName": "Eero Vasa",
    "lastTradedPrice": 1.79,
    "bsp": null,
    "inPlay": true
  },
  {
    "timestamp": 1779613603410,
    "marketId": "1.258542774",
    "selectionId": "38145316",
    "selectionName": "Giorgio Tabacco",
    "lastTradedPrice": 2.3,
    "bsp": null,
    "inPlay": true
  },
  {
    "timestamp": 1779613603410,
    "marketId": "1.258542774",
    "selectionId": "8713660",
    "selectionName": "Eero Vasa",
    "lastTradedPrice": 1.55,
    "bsp": null,
    "inPlay": true
  },
  {
    "timestamp": 1779613783412,
    "marketId": "1.258542774",
    "selectionId": "38145316",
    "selectionName": "Giorgio Tabacco",
    "lastTradedPrice": 2.3,
    "bsp": null,
    "inPlay": true
  },
  {
    "timestamp": 1779613783412,
    "marketId": "1.258542774",
    "selectionId": "8713660",
    "selectionName": "Eero Vasa",
    "lastTradedPrice": 1.76,
    "bsp": null,
    "inPlay": true
  },
  {
    "timestamp": 1779613873720,
    "marketId": "1.258542774",
    "selectionId": "38145316",
    "selectionName": "Giorgio Tabacco",
    "lastTradedPrice": 2.96,
    "bsp": null,
    "inPlay": true
  },
  {
    "timestamp": 1779613873720,
    "marketId": "1.258542774",
    "selectionId": "8713660",
    "selectionName": "Eero Vasa",
    "lastTradedPrice": 1.49,
    "bsp": null,
    "inPlay": true
  },
  {
    "timestamp": 1779613963787,
    "marketId": "1.258542774",
    "selectionId": "38145316",
    "selectionName": "Giorgio Tabacco",
    "lastTradedPrice": 3.9,
    "bsp": null,
    "inPlay": true
  },
  {
    "timestamp": 1779613963787,
    "marketId": "1.258542774",
    "selectionId": "8713660",
    "selectionName": "Eero Vasa",
    "lastTradedPrice": 1.32,
    "bsp": null,
    "inPlay": true
  },
  {
    "timestamp": 1779614053848,
    "marketId": "1.258542774",
    "selectionId": "38145316",
    "selectionName": "Giorgio Tabacco",
    "lastTradedPrice": 2.86,
    "bsp": null,
    "inPlay": true
  },
  {
    "timestamp": 1779614053848,
    "marketId": "1.258542774",
    "selectionId": "8713660",
    "selectionName": "Eero Vasa",
    "lastTradedPrice": 1.39,
    "bsp": null,
    "inPlay": true
  },
  {
    "timestamp": 1779614143912,
    "marketId": "1.258542774",
    "selectionId": "38145316",
    "selectionName": "Giorgio Tabacco",
    "lastTradedPrice": 2.28,
    "bsp": null,
    "inPlay": true
  },
  {
    "timestamp": 1779614143912,
    "marketId": "1.258542774",
    "selectionId": "8713660",
    "selectionName": "Eero Vasa",
    "lastTradedPrice": 1.75,
    "bsp": null,
    "inPlay": true
  },
  {
    "timestamp": 1779614233964,
    "marketId": "1.258542774",
    "selectionId": "38145316",
    "selectionName": "Giorgio Tabacco",
    "lastTradedPrice": 1.9,
    "bsp": null,
    "inPlay": true
  },
  {
    "timestamp": 1779614233964,
    "marketId": "1.258542774",
    "selectionId": "8713660",
    "selectionName": "Eero Vasa",
    "lastTradedPrice": 1.81,
    "bsp": null,
    "inPlay": true
  },
  {
    "timestamp": 1779614324012,
    "marketId": "1.258542774",
    "selectionId": "38145316",
    "selectionName": "Giorgio Tabacco",
    "lastTradedPrice": 1.83,
    "bsp": null,
    "inPlay": true
  },
  {
    "timestamp": 1779614324012,
    "marketId": "1.258542774",
    "selectionId": "8713660",
    "selectionName": "Eero Vasa",
    "lastTradedPrice": 2.08,
    "bsp": null,
    "inPlay": true
  },
  {
    "timestamp": 1779614414063,
    "marketId": "1.258542774",
    "selectionId": "38145316",
    "selectionName": "Giorgio Tabacco",
    "lastTradedPrice": 1.82,
    "bsp": null,
    "inPlay": true
  },
  {
    "timestamp": 1779614414063,
    "marketId": "1.258542774",
    "selectionId": "8713660",
    "selectionName": "Eero Vasa",
    "lastTradedPrice": 2.02,
    "bsp": null,
    "inPlay": true
  },
  {
    "timestamp": 1779614504129,
    "marketId": "1.258542774",
    "selectionId": "38145316",
    "selectionName": "Giorgio Tabacco",
    "lastTradedPrice": 2.18,
    "bsp": null,
    "inPlay": true
  },
  {
    "timestamp": 1779614504129,
    "marketId": "1.258542774",
    "selectionId": "8713660",
    "selectionName": "Eero Vasa",
    "lastTradedPrice": 1.83,
    "bsp": null,
    "inPlay": true
  },
  {
    "timestamp": 1779614594183,
    "marketId": "1.258542774",
    "selectionId": "38145316",
    "selectionName": "Giorgio Tabacco",
    "lastTradedPrice": 2.02,
    "bsp": null,
    "inPlay": true
  },
  {
    "timestamp": 1779614594183,
    "marketId": "1.258542774",
    "selectionId": "8713660",
    "selectionName": "Eero Vasa",
    "lastTradedPrice": 1.93,
    "bsp": null,
    "inPlay": true
  },
  {
    "timestamp": 1779614684237,
    "marketId": "1.258542774",
    "selectionId": "38145316",
    "selectionName": "Giorgio Tabacco",
    "lastTradedPrice": 1.9,
    "bsp": null,
    "inPlay": true
  },
  {
    "timestamp": 1779614684237,
    "marketId": "1.258542774",
    "selectionId": "8713660",
    "selectionName": "Eero Vasa",
    "lastTradedPrice": 1.99,
    "bsp": null,
    "inPlay": true
  },
  {
    "timestamp": 1779614774284,
    "marketId": "1.258542774",
    "selectionId": "38145316",
    "selectionName": "Giorgio Tabacco",
    "lastTradedPrice": 1.96,
    "bsp": null,
    "inPlay": true
  },
  {
    "timestamp": 1779614774284,
    "marketId": "1.258542774",
    "selectionId": "8713660",
    "selectionName": "Eero Vasa",
    "lastTradedPrice": 1.99,
    "bsp": null,
    "inPlay": true
  },
  {
    "timestamp": 1779614864335,
    "marketId": "1.258542774",
    "selectionId": "38145316",
    "selectionName": "Giorgio Tabacco",
    "lastTradedPrice": 1.73,
    "bsp": null,
    "inPlay": true
  },
  {
    "timestamp": 1779614864335,
    "marketId": "1.258542774",
    "selectionId": "8713660",
    "selectionName": "Eero Vasa",
    "lastTradedPrice": 1.85,
    "bsp": null,
    "inPlay": true
  },
  {
    "timestamp": 1779614954412,
    "marketId": "1.258542774",
    "selectionId": "38145316",
    "selectionName": "Giorgio Tabacco",
    "lastTradedPrice": 1.76,
    "bsp": null,
    "inPlay": true
  },
  {
    "timestamp": 1779614954412,
    "marketId": "1.258542774",
    "selectionId": "8713660",
    "selectionName": "Eero Vasa",
    "lastTradedPrice": 1.84,
    "bsp": null,
    "inPlay": true
  },
  {
    "timestamp": 1779615044462,
    "marketId": "1.258542774",
    "selectionId": "38145316",
    "selectionName": "Giorgio Tabacco",
    "lastTradedPrice": 1.87,
    "bsp": null,
    "inPlay": true
  },
  {
    "timestamp": 1779615044462,
    "marketId": "1.258542774",
    "selectionId": "8713660",
    "selectionName": "Eero Vasa",
    "lastTradedPrice": 2.1,
    "bsp": null,
    "inPlay": true
  },
  {
    "timestamp": 1779615134506,
    "marketId": "1.258542774",
    "selectionId": "38145316",
    "selectionName": "Giorgio Tabacco",
    "lastTradedPrice": 2.2,
    "bsp": null,
    "inPlay": true
  },
  {
    "timestamp": 1779615134506,
    "marketId": "1.258542774",
    "selectionId": "8713660",
    "selectionName": "Eero Vasa",
    "lastTradedPrice": 1.77,
    "bsp": null,
    "inPlay": true
  },
  {
    "timestamp": 1779615224539,
    "marketId": "1.258542774",
    "selectionId": "38145316",
    "selectionName": "Giorgio Tabacco",
    "lastTradedPrice": 2.94,
    "bsp": null,
    "inPlay": true
  },
  {
    "timestamp": 1779615224539,
    "marketId": "1.258542774",
    "selectionId": "8713660",
    "selectionName": "Eero Vasa",
    "lastTradedPrice": 1.5,
    "bsp": null,
    "inPlay": true
  },
  {
    "timestamp": 1779615314595,
    "marketId": "1.258542774",
    "selectionId": "38145316",
    "selectionName": "Giorgio Tabacco",
    "lastTradedPrice": 2.74,
    "bsp": null,
    "inPlay": true
  },
  {
    "timestamp": 1779615314595,
    "marketId": "1.258542774",
    "selectionId": "8713660",
    "selectionName": "Eero Vasa",
    "lastTradedPrice": 1.17,
    "bsp": null,
    "inPlay": true
  },
  {
    "timestamp": 1779615494599,
    "marketId": "1.258542774",
    "selectionId": "38145316",
    "selectionName": "Giorgio Tabacco",
    "lastTradedPrice": 2.6,
    "bsp": null,
    "inPlay": true
  },
  {
    "timestamp": 1779615494599,
    "marketId": "1.258542774",
    "selectionId": "8713660",
    "selectionName": "Eero Vasa",
    "lastTradedPrice": 1.62,
    "bsp": null,
    "inPlay": true
  },
  {
    "timestamp": 1779615494718,
    "marketId": "1.258542774",
    "selectionId": "38145316",
    "selectionName": "Giorgio Tabacco",
    "lastTradedPrice": 2.6,
    "bsp": null,
    "inPlay": true
  },
  {
    "timestamp": 1779615494718,
    "marketId": "1.258542774",
    "selectionId": "8713660",
    "selectionName": "Eero Vasa",
    "lastTradedPrice": 1.62,
    "bsp": null,
    "inPlay": true
  },
  {
    "timestamp": 1779615584753,
    "marketId": "1.258542774",
    "selectionId": "38145316",
    "selectionName": "Giorgio Tabacco",
    "lastTradedPrice": 1.6,
    "bsp": null,
    "inPlay": true
  },
  {
    "timestamp": 1779615584753,
    "marketId": "1.258542774",
    "selectionId": "8713660",
    "selectionName": "Eero Vasa",
    "lastTradedPrice": 1.82,
    "bsp": null,
    "inPlay": true
  },
  {
    "timestamp": 1779615674801,
    "marketId": "1.258542774",
    "selectionId": "38145316",
    "selectionName": "Giorgio Tabacco",
    "lastTradedPrice": 1.01,
    "bsp": null,
    "inPlay": true
  },
  {
    "timestamp": 1779615674801,
    "marketId": "1.258542774",
    "selectionId": "8713660",
    "selectionName": "Eero Vasa",
    "lastTradedPrice": 1.81,
    "bsp": null,
    "inPlay": true
  },
  {
    "timestamp": 1779615764850,
    "marketId": "1.258542774",
    "selectionId": "38145316",
    "selectionName": "Giorgio Tabacco",
    "lastTradedPrice": 1.45,
    "bsp": null,
    "inPlay": true
  },
  {
    "timestamp": 1779615764850,
    "marketId": "1.258542774",
    "selectionId": "8713660",
    "selectionName": "Eero Vasa",
    "lastTradedPrice": 1.79,
    "bsp": null,
    "inPlay": true
  },
  {
    "timestamp": 1779615854905,
    "marketId": "1.258542774",
    "selectionId": "38145316",
    "selectionName": "Giorgio Tabacco",
    "lastTradedPrice": 1.45,
    "bsp": null,
    "inPlay": true
  },
  {
    "timestamp": 1779615854905,
    "marketId": "1.258542774",
    "selectionId": "8713660",
    "selectionName": "Eero Vasa",
    "lastTradedPrice": 1.79,
    "bsp": null,
    "inPlay": true
  },
  {
    "timestamp": 1779615944958,
    "marketId": "1.258542774",
    "selectionId": "38145316",
    "selectionName": "Giorgio Tabacco",
    "lastTradedPrice": 1.01,
    "bsp": null,
    "inPlay": true
  },
  {
    "timestamp": 1779615944958,
    "marketId": "1.258542774",
    "selectionId": "8713660",
    "selectionName": "Eero Vasa",
    "lastTradedPrice": 1.01,
    "bsp": null,
    "inPlay": true
  },
  {
    "timestamp": 1779616034991,
    "marketId": "1.258542774",
    "selectionId": "38145316",
    "selectionName": "Giorgio Tabacco",
    "lastTradedPrice": 1.22,
    "bsp": null,
    "inPlay": true
  },
  {
    "timestamp": 1779616034991,
    "marketId": "1.258542774",
    "selectionId": "8713660",
    "selectionName": "Eero Vasa",
    "lastTradedPrice": 5.2,
    "bsp": null,
    "inPlay": true
  },
  {
    "timestamp": 1779616125044,
    "marketId": "1.258542774",
    "selectionId": "38145316",
    "selectionName": "Giorgio Tabacco",
    "lastTradedPrice": 1.38,
    "bsp": null,
    "inPlay": true
  },
  {
    "timestamp": 1779616125044,
    "marketId": "1.258542774",
    "selectionId": "8713660",
    "selectionName": "Eero Vasa",
    "lastTradedPrice": 3.3,
    "bsp": null,
    "inPlay": true
  },
  {
    "timestamp": 1779616215074,
    "marketId": "1.258542774",
    "selectionId": "38145316",
    "selectionName": "Giorgio Tabacco",
    "lastTradedPrice": 1.51,
    "bsp": null,
    "inPlay": true
  },
  {
    "timestamp": 1779616215074,
    "marketId": "1.258542774",
    "selectionId": "8713660",
    "selectionName": "Eero Vasa",
    "lastTradedPrice": 2.92,
    "bsp": null,
    "inPlay": true
  },
  {
    "timestamp": 1779616305128,
    "marketId": "1.258542774",
    "selectionId": "38145316",
    "selectionName": "Giorgio Tabacco",
    "lastTradedPrice": 1.54,
    "bsp": null,
    "inPlay": true
  },
  {
    "timestamp": 1779616305128,
    "marketId": "1.258542774",
    "selectionId": "8713660",
    "selectionName": "Eero Vasa",
    "lastTradedPrice": 2.36,
    "bsp": null,
    "inPlay": true
  },
  {
    "timestamp": 1779616395177,
    "marketId": "1.258542774",
    "selectionId": "38145316",
    "selectionName": "Giorgio Tabacco",
    "lastTradedPrice": 1.41,
    "bsp": null,
    "inPlay": true
  },
  {
    "timestamp": 1779616395177,
    "marketId": "1.258542774",
    "selectionId": "8713660",
    "selectionName": "Eero Vasa",
    "lastTradedPrice": 3.05,
    "bsp": null,
    "inPlay": true
  },
  {
    "timestamp": 1779616485225,
    "marketId": "1.258542774",
    "selectionId": "38145316",
    "selectionName": "Giorgio Tabacco",
    "lastTradedPrice": 1.37,
    "bsp": null,
    "inPlay": true
  },
  {
    "timestamp": 1779616485225,
    "marketId": "1.258542774",
    "selectionId": "8713660",
    "selectionName": "Eero Vasa",
    "lastTradedPrice": 3.4,
    "bsp": null,
    "inPlay": true
  },
  {
    "timestamp": 1779616575275,
    "marketId": "1.258542774",
    "selectionId": "38145316",
    "selectionName": "Giorgio Tabacco",
    "lastTradedPrice": 1.15,
    "bsp": null,
    "inPlay": true
  },
  {
    "timestamp": 1779616575275,
    "marketId": "1.258542774",
    "selectionId": "8713660",
    "selectionName": "Eero Vasa",
    "lastTradedPrice": 6.6,
    "bsp": null,
    "inPlay": true
  },
  {
    "timestamp": 1779616665335,
    "marketId": "1.258542774",
    "selectionId": "38145316",
    "selectionName": "Giorgio Tabacco",
    "lastTradedPrice": 1.14,
    "bsp": null,
    "inPlay": true
  },
  {
    "timestamp": 1779616665335,
    "marketId": "1.258542774",
    "selectionId": "8713660",
    "selectionName": "Eero Vasa",
    "lastTradedPrice": 7,
    "bsp": null,
    "inPlay": true
  },
  {
    "timestamp": 1779616755385,
    "marketId": "1.258542774",
    "selectionId": "38145316",
    "selectionName": "Giorgio Tabacco",
    "lastTradedPrice": 1.09,
    "bsp": null,
    "inPlay": true
  },
  {
    "timestamp": 1779616755385,
    "marketId": "1.258542774",
    "selectionId": "8713660",
    "selectionName": "Eero Vasa",
    "lastTradedPrice": 10,
    "bsp": null,
    "inPlay": true
  },
  {
    "timestamp": 1779616845430,
    "marketId": "1.258542774",
    "selectionId": "38145316",
    "selectionName": "Giorgio Tabacco",
    "lastTradedPrice": 1.1,
    "bsp": null,
    "inPlay": true
  },
  {
    "timestamp": 1779616845430,
    "marketId": "1.258542774",
    "selectionId": "8713660",
    "selectionName": "Eero Vasa",
    "lastTradedPrice": 10,
    "bsp": null,
    "inPlay": true
  },
  {
    "timestamp": 1779616935481,
    "marketId": "1.258542774",
    "selectionId": "38145316",
    "selectionName": "Giorgio Tabacco",
    "lastTradedPrice": 1.07,
    "bsp": null,
    "inPlay": true
  },
  {
    "timestamp": 1779616935481,
    "marketId": "1.258542774",
    "selectionId": "8713660",
    "selectionName": "Eero Vasa",
    "lastTradedPrice": 11,
    "bsp": null,
    "inPlay": true
  },
  {
    "timestamp": 1779617115487,
    "marketId": "1.258542774",
    "selectionId": "38145316",
    "selectionName": "Giorgio Tabacco",
    "lastTradedPrice": 1.1,
    "bsp": null,
    "inPlay": true
  },
  {
    "timestamp": 1779617115487,
    "marketId": "1.258542774",
    "selectionId": "8713660",
    "selectionName": "Eero Vasa",
    "lastTradedPrice": 9.4,
    "bsp": null,
    "inPlay": true
  },
  {
    "timestamp": 1779617115587,
    "marketId": "1.258542774",
    "selectionId": "38145316",
    "selectionName": "Giorgio Tabacco",
    "lastTradedPrice": 1.1,
    "bsp": null,
    "inPlay": true
  },
  {
    "timestamp": 1779617115587,
    "marketId": "1.258542774",
    "selectionId": "8713660",
    "selectionName": "Eero Vasa",
    "lastTradedPrice": 9.4,
    "bsp": null,
    "inPlay": true
  },
  {
    "timestamp": 1779617295593,
    "marketId": "1.258542774",
    "selectionId": "38145316",
    "selectionName": "Giorgio Tabacco",
    "lastTradedPrice": 1.21,
    "bsp": null,
    "inPlay": true
  },
  {
    "timestamp": 1779617295593,
    "marketId": "1.258542774",
    "selectionId": "8713660",
    "selectionName": "Eero Vasa",
    "lastTradedPrice": 5.6,
    "bsp": null,
    "inPlay": true
  },
  {
    "timestamp": 1779617295691,
    "marketId": "1.258542774",
    "selectionId": "38145316",
    "selectionName": "Giorgio Tabacco",
    "lastTradedPrice": 1.21,
    "bsp": null,
    "inPlay": true
  },
  {
    "timestamp": 1779617295691,
    "marketId": "1.258542774",
    "selectionId": "8713660",
    "selectionName": "Eero Vasa",
    "lastTradedPrice": 5.6,
    "bsp": null,
    "inPlay": true
  },
  {
    "timestamp": 1779617385739,
    "marketId": "1.258542774",
    "selectionId": "38145316",
    "selectionName": "Giorgio Tabacco",
    "lastTradedPrice": 1.32,
    "bsp": null,
    "inPlay": true
  },
  {
    "timestamp": 1779617385739,
    "marketId": "1.258542774",
    "selectionId": "8713660",
    "selectionName": "Eero Vasa",
    "lastTradedPrice": 3.15,
    "bsp": null,
    "inPlay": true
  },
  {
    "timestamp": 1779617475786,
    "marketId": "1.258542774",
    "selectionId": "38145316",
    "selectionName": "Giorgio Tabacco",
    "lastTradedPrice": 1.6,
    "bsp": null,
    "inPlay": true
  },
  {
    "timestamp": 1779617475786,
    "marketId": "1.258542774",
    "selectionId": "8713660",
    "selectionName": "Eero Vasa",
    "lastTradedPrice": 2.66,
    "bsp": null,
    "inPlay": true
  },
  {
    "timestamp": 1779617655791,
    "marketId": "1.258542774",
    "selectionId": "38145316",
    "selectionName": "Giorgio Tabacco",
    "lastTradedPrice": 1.37,
    "bsp": null,
    "inPlay": true
  },
  {
    "timestamp": 1779617655791,
    "marketId": "1.258542774",
    "selectionId": "8713660",
    "selectionName": "Eero Vasa",
    "lastTradedPrice": 3.4,
    "bsp": null,
    "inPlay": true
  },
  {
    "timestamp": 1779617655892,
    "marketId": "1.258542774",
    "selectionId": "38145316",
    "selectionName": "Giorgio Tabacco",
    "lastTradedPrice": 1.37,
    "bsp": null,
    "inPlay": true
  },
  {
    "timestamp": 1779617655892,
    "marketId": "1.258542774",
    "selectionId": "8713660",
    "selectionName": "Eero Vasa",
    "lastTradedPrice": 3.4,
    "bsp": null,
    "inPlay": true
  },
  {
    "timestamp": 1779617745943,
    "marketId": "1.258542774",
    "selectionId": "38145316",
    "selectionName": "Giorgio Tabacco",
    "lastTradedPrice": 1.25,
    "bsp": null,
    "inPlay": true
  },
  {
    "timestamp": 1779617745943,
    "marketId": "1.258542774",
    "selectionId": "8713660",
    "selectionName": "Eero Vasa",
    "lastTradedPrice": 4.5,
    "bsp": null,
    "inPlay": true
  },
  {
    "timestamp": 1779617835996,
    "marketId": "1.258542774",
    "selectionId": "38145316",
    "selectionName": "Giorgio Tabacco",
    "lastTradedPrice": 1.21,
    "bsp": null,
    "inPlay": true
  },
  {
    "timestamp": 1779617835996,
    "marketId": "1.258542774",
    "selectionId": "8713660",
    "selectionName": "Eero Vasa",
    "lastTradedPrice": 3.1,
    "bsp": null,
    "inPlay": true
  },
  {
    "timestamp": 1779617926067,
    "marketId": "1.258542774",
    "selectionId": "38145316",
    "selectionName": "Giorgio Tabacco",
    "lastTradedPrice": 1.2,
    "bsp": null,
    "inPlay": true
  },
  {
    "timestamp": 1779617926067,
    "marketId": "1.258542774",
    "selectionId": "8713660",
    "selectionName": "Eero Vasa",
    "lastTradedPrice": 3.15,
    "bsp": null,
    "inPlay": true
  },
  {
    "timestamp": 1779618016097,
    "marketId": "1.258542774",
    "selectionId": "38145316",
    "selectionName": "Giorgio Tabacco",
    "lastTradedPrice": 1.34,
    "bsp": null,
    "inPlay": true
  },
  {
    "timestamp": 1779618016097,
    "marketId": "1.258542774",
    "selectionId": "8713660",
    "selectionName": "Eero Vasa",
    "lastTradedPrice": 3,
    "bsp": null,
    "inPlay": true
  },
  {
    "timestamp": 1779618106158,
    "marketId": "1.258542774",
    "selectionId": "38145316",
    "selectionName": "Giorgio Tabacco",
    "lastTradedPrice": 1.53,
    "bsp": null,
    "inPlay": true
  },
  {
    "timestamp": 1779618106158,
    "marketId": "1.258542774",
    "selectionId": "8713660",
    "selectionName": "Eero Vasa",
    "lastTradedPrice": 2.8,
    "bsp": null,
    "inPlay": true
  },
  {
    "timestamp": 1779618196198,
    "marketId": "1.258542774",
    "selectionId": "38145316",
    "selectionName": "Giorgio Tabacco",
    "lastTradedPrice": 1.4,
    "bsp": null,
    "inPlay": true
  },
  {
    "timestamp": 1779618196198,
    "marketId": "1.258542774",
    "selectionId": "8713660",
    "selectionName": "Eero Vasa",
    "lastTradedPrice": 3.3,
    "bsp": null,
    "inPlay": true
  },
  {
    "timestamp": 1779618286242,
    "marketId": "1.258542774",
    "selectionId": "38145316",
    "selectionName": "Giorgio Tabacco",
    "lastTradedPrice": 1.37,
    "bsp": null,
    "inPlay": true
  },
  {
    "timestamp": 1779618286242,
    "marketId": "1.258542774",
    "selectionId": "8713660",
    "selectionName": "Eero Vasa",
    "lastTradedPrice": 3.55,
    "bsp": null,
    "inPlay": true
  },
  {
    "timestamp": 1779618376300,
    "marketId": "1.258542774",
    "selectionId": "38145316",
    "selectionName": "Giorgio Tabacco",
    "lastTradedPrice": 1.18,
    "bsp": null,
    "inPlay": true
  },
  {
    "timestamp": 1779618376300,
    "marketId": "1.258542774",
    "selectionId": "8713660",
    "selectionName": "Eero Vasa",
    "lastTradedPrice": 6,
    "bsp": null,
    "inPlay": true
  },
  {
    "timestamp": 1779618466565,
    "marketId": "1.258542774",
    "selectionId": "38145316",
    "selectionName": "Giorgio Tabacco",
    "lastTradedPrice": 1.05,
    "bsp": null,
    "inPlay": true
  },
  {
    "timestamp": 1779618466565,
    "marketId": "1.258542774",
    "selectionId": "8713660",
    "selectionName": "Eero Vasa",
    "lastTradedPrice": 18.5,
    "bsp": null,
    "inPlay": true
  },
  {
    "timestamp": 1779618556617,
    "marketId": "1.258542774",
    "selectionId": "38145316",
    "selectionName": "Giorgio Tabacco",
    "lastTradedPrice": 1.04,
    "bsp": null,
    "inPlay": true
  },
  {
    "timestamp": 1779618556617,
    "marketId": "1.258542774",
    "selectionId": "8713660",
    "selectionName": "Eero Vasa",
    "lastTradedPrice": 10.5,
    "bsp": null,
    "inPlay": true
  },
  {
    "timestamp": 1779618646656,
    "marketId": "1.258542774",
    "selectionId": "38145316",
    "selectionName": "Giorgio Tabacco",
    "lastTradedPrice": 1.04,
    "bsp": null,
    "inPlay": true
  },
  {
    "timestamp": 1779618646656,
    "marketId": "1.258542774",
    "selectionId": "8713660",
    "selectionName": "Eero Vasa",
    "lastTradedPrice": 100,
    "bsp": null,
    "inPlay": true
  }
]