[
  {
    "timestamp": 1776774872915,
    "marketId": "1.257063309",
    "selectionId": "9304685",
    "selectionName": "Anna Bondar",
    "lastTradedPrice": 1.22,
    "bsp": null,
    "inPlay": true
  },
  {
    "timestamp": 1776774872915,
    "marketId": "1.257063309",
    "selectionId": "7283232",
    "selectionName": "Viktorija Golubic",
    "lastTradedPrice": 5.3,
    "bsp": null,
    "inPlay": true
  },
  {
    "timestamp": 1776775052867,
    "marketId": "1.257063309",
    "selectionId": "9304685",
    "selectionName": "Anna Bondar",
    "lastTradedPrice": 1.27,
    "bsp": null,
    "inPlay": true
  },
  {
    "timestamp": 1776775052867,
    "marketId": "1.257063309",
    "selectionId": "7283232",
    "selectionName": "Viktorija Golubic",
    "lastTradedPrice": 4.6,
    "bsp": null,
    "inPlay": true
  },
  {
    "timestamp": 1776775174551,
    "marketId": "1.257063309",
    "selectionId": "9304685",
    "selectionName": "Anna Bondar",
    "lastTradedPrice": 1.3,
    "bsp": null,
    "inPlay": true
  },
  {
    "timestamp": 1776775174551,
    "marketId": "1.257063309",
    "selectionId": "7283232",
    "selectionName": "Viktorija Golubic",
    "lastTradedPrice": 4.3,
    "bsp": null,
    "inPlay": true
  },
  {
    "timestamp": 1776775354554,
    "marketId": "1.257063309",
    "selectionId": "9304685",
    "selectionName": "Anna Bondar",
    "lastTradedPrice": 1.19,
    "bsp": null,
    "inPlay": true
  },
  {
    "timestamp": 1776775354554,
    "marketId": "1.257063309",
    "selectionId": "7283232",
    "selectionName": "Viktorija Golubic",
    "lastTradedPrice": 5,
    "bsp": null,
    "inPlay": true
  },
  {
    "timestamp": 1776775475855,
    "marketId": "1.257063309",
    "selectionId": "9304685",
    "selectionName": "Anna Bondar",
    "lastTradedPrice": 1.23,
    "bsp": null,
    "inPlay": true
  },
  {
    "timestamp": 1776775475855,
    "marketId": "1.257063309",
    "selectionId": "7283232",
    "selectionName": "Viktorija Golubic",
    "lastTradedPrice": 4.2,
    "bsp": null,
    "inPlay": true
  },
  {
    "timestamp": 1776775655858,
    "marketId": "1.257063309",
    "selectionId": "9304685",
    "selectionName": "Anna Bondar",
    "lastTradedPrice": 1.28,
    "bsp": null,
    "inPlay": true
  },
  {
    "timestamp": 1776775655858,
    "marketId": "1.257063309",
    "selectionId": "7283232",
    "selectionName": "Viktorija Golubic",
    "lastTradedPrice": 3.75,
    "bsp": null,
    "inPlay": true
  },
  {
    "timestamp": 1776775777778,
    "marketId": "1.257063309",
    "selectionId": "9304685",
    "selectionName": "Anna Bondar",
    "lastTradedPrice": 1.25,
    "bsp": null,
    "inPlay": true
  },
  {
    "timestamp": 1776775777778,
    "marketId": "1.257063309",
    "selectionId": "7283232",
    "selectionName": "Viktorija Golubic",
    "lastTradedPrice": 4.7,
    "bsp": null,
    "inPlay": true
  },
  {
    "timestamp": 1776775957781,
    "marketId": "1.257063309",
    "selectionId": "9304685",
    "selectionName": "Anna Bondar",
    "lastTradedPrice": 1.12,
    "bsp": null,
    "inPlay": true
  },
  {
    "timestamp": 1776775957781,
    "marketId": "1.257063309",
    "selectionId": "7283232",
    "selectionName": "Viktorija Golubic",
    "lastTradedPrice": 8.8,
    "bsp": null,
    "inPlay": true
  },
  {
    "timestamp": 1776776079085,
    "marketId": "1.257063309",
    "selectionId": "9304685",
    "selectionName": "Anna Bondar",
    "lastTradedPrice": 1.11,
    "bsp": null,
    "inPlay": true
  },
  {
    "timestamp": 1776776079085,
    "marketId": "1.257063309",
    "selectionId": "7283232",
    "selectionName": "Viktorija Golubic",
    "lastTradedPrice": 9.6,
    "bsp": null,
    "inPlay": true
  },
  {
    "timestamp": 1776776259089,
    "marketId": "1.257063309",
    "selectionId": "9304685",
    "selectionName": "Anna Bondar",
    "lastTradedPrice": 1.07,
    "bsp": null,
    "inPlay": true
  },
  {
    "timestamp": 1776776259089,
    "marketId": "1.257063309",
    "selectionId": "7283232",
    "selectionName": "Viktorija Golubic",
    "lastTradedPrice": 13.5,
    "bsp": null,
    "inPlay": true
  },
  {
    "timestamp": 1776776381110,
    "marketId": "1.257063309",
    "selectionId": "9304685",
    "selectionName": "Anna Bondar",
    "lastTradedPrice": 1.04,
    "bsp": null,
    "inPlay": true
  },
  {
    "timestamp": 1776776381110,
    "marketId": "1.257063309",
    "selectionId": "7283232",
    "selectionName": "Viktorija Golubic",
    "lastTradedPrice": 23,
    "bsp": null,
    "inPlay": true
  },
  {
    "timestamp": 1776776561114,
    "marketId": "1.257063309",
    "selectionId": "9304685",
    "selectionName": "Anna Bondar",
    "lastTradedPrice": 1.03,
    "bsp": null,
    "inPlay": true
  },
  {
    "timestamp": 1776776561114,
    "marketId": "1.257063309",
    "selectionId": "7283232",
    "selectionName": "Viktorija Golubic",
    "lastTradedPrice": 28,
    "bsp": null,
    "inPlay": true
  }
]